manwrapper/__init__.py
manwrapper/main.py
tests/__init__.py
tests/test_manwrapper.py
manwrapper-0.4.dist-info/LICENSE
manwrapper-0.4.dist-info/METADATA
manwrapper-0.4.dist-info/WHEEL
manwrapper-0.4.dist-info/entry_points.txt
manwrapper-0.4.dist-info/top_level.txt
manwrapper-0.4.dist-info/RECORD
