Metadata-Version: 2.1
Name: manwrapper
Version: 0.4
Summary: A simple command-line tool to view man pages.
Home-page: https://github.com/bet0x/manwrapper
Author: Alberto Ferrer
Author-email: albertof@barrahome.org
Classifier: Programming Language :: Python :: 3
Classifier: License :: OSI Approved :: MIT License
Classifier: Operating System :: OS Independent
License-File: LICENSE
